slacker/__init__.py
slacker/message_builder.py
slacker/sender.py
slacker/status_manager.py
sci_slacker-0.0.1.dist-info/LICENSE
sci_slacker-0.0.1.dist-info/METADATA
sci_slacker-0.0.1.dist-info/WHEEL
sci_slacker-0.0.1.dist-info/top_level.txt
sci_slacker-0.0.1.dist-info/RECORD
