Metadata-Version: 2.1
Name: sci-slacker
Version: 0.0.1
Summary: A tiny tool for sending experiment status to Slack client.
Home-page: https://github.com/Luolc/Slacker
Author: Liangchen Luo
Author-email: luolc.witty@gmail.com
License: Apache
Keywords: slack
Platform: UNKNOWN
Classifier: Intended Audience :: Science/Research
Classifier: Development Status :: 3 - Alpha
Classifier: License :: OSI Approved :: Apache Software License
Classifier: Programming Language :: Python :: 3
Classifier: Programming Language :: Python :: 3.5
Classifier: Programming Language :: Python :: 3.6
Classifier: Programming Language :: Python :: 3.7
Requires-Python: >=3.5.0
Requires-Dist: slackclient (>=2.1.0)
